stringy/__init__.py
stringy/main.py
stringy-0.1.0.dist-info/METADATA
stringy-0.1.0.dist-info/WHEEL
stringy-0.1.0.dist-info/top_level.txt
stringy-0.1.0.dist-info/RECORD
