Metadata-Version: 2.4
Name: stringy
Version: 0.1.0
Summary: Basic manipulation for text
Author: EDCode
Author-email: ed.code.tech@gmail.com
Classifier: Programming Language :: Python :: 3
Classifier: Operating System :: OS Independent
Requires-Python: >=3.6
Dynamic: author
Dynamic: author-email
Dynamic: classifier
Dynamic: requires-python
Dynamic: summary
